sipy/__init__.py
sipy/automap.py
sipy/config.py
sipy/definitions.py
sipy/quantities/__init__.py
sipy/quantities/base_quantity.py
sipy/quantities/constants.py
sipy/quantities/defined_quantities.py
sipy/sipy.toml
sipy/units/__init__.py
sipy/units/base_unit.py
sipy/units/defined_units.py
sipy/units/prefixes.py
sipy-0.3.1.dist-info/LICENSE
sipy-0.3.1.dist-info/WHEEL
sipy-0.3.1.dist-info/METADATA
sipy-0.3.1.dist-info/RECORD
