Metadata-Version: 2.1
Name: sipy
Version: 0.3.1
Summary: 
Home-page: https://broster.gitlab.io/sipy/
Author: Samuel Broster
Author-email: s.h.broster+gitlab@pm.me
Requires-Python: >=3.6,<4.0
Classifier: Programming Language :: Python :: 3
Classifier: Programming Language :: Python :: 3.6
Classifier: Programming Language :: Python :: 3.7
Classifier: Programming Language :: Python :: 3.8
Requires-Dist: toml (>=0.10.0,<0.11.0)
Project-URL: Documentation, https://broster.gitlab.io/sipy/
Project-URL: Repository, https://gitlab.com/broster/sipy
